CHANGES.txt
LICENSE.txt
MANIFEST.in
README.txt
setup.py
aodag/__init__.py
aodag.scaffold.egg-info/PKG-INFO
aodag.scaffold.egg-info/SOURCES.txt
aodag.scaffold.egg-info/dependency_links.txt
aodag.scaffold.egg-info/entry_points.txt
aodag.scaffold.egg-info/namespace_packages.txt
aodag.scaffold.egg-info/top_level.txt
aodag/scaffold/__init__.py
aodag/scaffold/commands.py
aodag/scaffold/tests.py